{"id":"00753B40","program":"ST.exe","address":"00753B40","name":"FUN_00753b40","qualified_name":"FUN_00753b40","namespace":"Global","source":"DEFAULT","size":62,"signature":"int __stdcall FUN_00753b40(int param_1)","calling_convention":"__stdcall","parameter_count":1,"local_variable_count":0,"stack_frame_size":8,"thunk":false,"external":false,"inline":false,"noreturn":false,"varargs":false,"library":false,"body_exported":true,"decompile_status":"ok","tags":[],"callers":["00750BA0 Library::DKW::DB::FUN_00750ba0","00754FD0 FUN_00754fd0","00755560 FUN_00755560","00755830 FUN_00755830"],"callees":["006D4A40 Library::DKW::FMM::FUN_006d4a40"],"referenced_strings":[],"referenced_globals":[],"comments":[],"parameters":[{"name":"param_1","type":"int","length":4,"storage":"Stack[0x4]:4","comment":"","source":"DEFAULT"}],"locals":[]}
