{"id":"006CEBE0","program":"ST.exe","address":"006CEBE0","name":"FUN_006cebe0","qualified_name":"FUN_006cebe0","namespace":"Global","source":"DEFAULT","size":93,"signature":"undefined __stdcall FUN_006cebe0(char * param_1, int param_2, char * param_3, int param_4, int param_5, int param_6, char param_7)","calling_convention":"__stdcall","parameter_count":7,"local_variable_count":0,"stack_frame_size":29,"thunk":false,"external":false,"inline":false,"noreturn":false,"varargs":false,"library":false,"body_exported":true,"decompile_status":"ok","tags":[],"callers":["006B0330 FUN_006b0330","006B03D0 FUN_006b03d0","006B5110 Library::DKW::WGR::FUN_006b5110","006CEF60 FUN_006cef60","006D0CF0 FUN_006d0cf0"],"callees":[],"referenced_strings":[],"referenced_globals":[],"comments":[],"parameters":[{"name":"param_1","type":"char *","length":4,"storage":"Stack[0x4]:4","comment":"","source":"DEFAULT"},{"name":"param_2","type":"int","length":4,"storage":"Stack[0x8]:4","comment":"","source":"DEFAULT"},{"name":"param_3","type":"char *","length":4,"storage":"Stack[0xc]:4","comment":"","source":"DEFAULT"},{"name":"param_4","type":"int","length":4,"storage":"Stack[0x10]:4","comment":"","source":"DEFAULT"},{"name":"param_5","type":"int","length":4,"storage":"Stack[0x14]:4","comment":"","source":"DEFAULT"},{"name":"param_6","type":"int","length":4,"storage":"Stack[0x18]:4","comment":"","source":"DEFAULT"},{"name":"param_7","type":"char","length":1,"storage":"Stack[0x1c]:1","comment":"","source":"DEFAULT"}],"locals":[]}
