{"id":"005BF860","program":"ST.exe","address":"005BF860","name":"NoneMReport","qualified_name":"MReportTy::NoneMReport","namespace":"MReportTy","source":"USER_DEFINED","size":973,"signature":"undefined __thiscall NoneMReport(MReportTy * this)","calling_convention":"__thiscall","parameter_count":1,"local_variable_count":4,"stack_frame_size":84,"thunk":false,"external":false,"inline":false,"noreturn":false,"varargs":false,"library":false,"body_exported":true,"decompile_status":"ok","tags":["RECOVERED_DEBUG_NAME"],"callers":[],"callees":["0040128A HoloTy::Done","004016FE MReportTy::PaintMainScore","00402298 thunk_FUN_00540620","00403A6C thunk_FUN_005c0230","00404BF1 thunk_FUN_005b6730","00404DB8 thunk_FUN_005b66e0","004055F1 HoloTy::NextFas","006A5E40 RaiseInternalException","006AD4D0 ReportDebugMessage","006B3AF0 FUN_006b3af0","006B48E0 Library::DKW::DDX::FUN_006b48e0","006B5F80 FUN_006b5f80","0072D7F0 Library::MSVCRT::__setjmp3","0072E2B0 Library::MSVCRT::FUN_0072e2b0"],"referenced_strings":["007CCEC8 s_E:\\__titans\\Start\\rpt_obj.cpp_007ccec8 = \"E:\\\\__titans\\\\Start\\\\rpt_obj.cpp\"","007CCFC8 s_MReportTy::NoneMReport_007ccfc8 = \"MReportTy::NoneMReport\""],"referenced_globals":["007A4CCC DAT_007a4ccc = 25h %","00806730 DAT_00806730 = 00000000h","00806734 DAT_00806734 = 00000000h","0080759C DAT_0080759c = 00000000h","008075A8 DAT_008075a8 = 00000000h","0080C83E DAT_0080c83e = 00h","0080C943 DAT_0080c943 = 00000000h","0080C947 DAT_0080c947 = 00000000h","0080C963 DAT_0080c963 = 00000000h","00858DF8 g_currentExceptionFrame = 00000000"],"comments":["005BF860 [plate] Recovered from embedded debug metadata: E:\\__titans\\Start\\rpt_obj.cpp MReportTy::NoneMReport"],"parameters":[{"name":"this","type":"MReportTy *","length":4,"storage":"ECX:4 (auto)","comment":"","source":"ANALYSIS"}],"locals":[{"name":"local_8","type":"undefined4","length":4,"storage":"Stack[-0x8]:4","comment":"","source":"DEFAULT"},{"name":"local_c","type":"undefined4","length":4,"storage":"Stack[-0xc]:4","comment":"","source":"DEFAULT"},{"name":"local_4c","type":"undefined","length":1,"storage":"Stack[-0x4c]:1","comment":"","source":"DEFAULT"},{"name":"local_50","type":"undefined4","length":4,"storage":"Stack[-0x50]:4","comment":"","source":"DEFAULT"}]}
