{"start":"004D8DF0","end":"004D8E0B","length":28,"block":".text","classification":"defined_data","base_kind":"defined_data","printable_bytes":7,"non_padding_bytes":21,"executable_pointer_count":7,"valid_relative_call_count":0,"return_opcode_count":2,"import_thunk_entry_count":0,"pointer_targets":["004D8DF0 -> 004D8DC2","004D8DF4 -> 004D8DDE","004D8DF8 -> 004D8DEC","004D8DFC -> 004D8DEC","004D8E00 -> 004D8DEC","004D8E04 -> 004D8DC2","004D8E08 -> 004D8DDE"],"raw_inbound_pointer_count":0,"raw_inbound_pointer_sources":[],"raw_pointer_linked_control_flow_entries":0,"raw_pointer_linked_control_flow_sources":[],"inbound_references":["004D8DBB -> 004D8DF0 DATA"]}
