{"id":"004DE410","program":"ST.exe","address":"004DE410","name":"FUN_004de410","qualified_name":"FUN_004de410","namespace":"Global","source":"DEFAULT","size":170,"signature":"int __stdcall FUN_004de410(void * param_1, int param_2, int param_3)","calling_convention":"__stdcall","parameter_count":3,"local_variable_count":2,"stack_frame_size":28,"thunk":false,"external":false,"inline":false,"noreturn":false,"varargs":false,"decompile_status":"ok","tags":[],"callers":[],"callees":["00401861 thunk_FUN_004ddc30","00402B4E thunk_FUN_004ddb30","006ACC70 FUN_006acc70"],"referenced_strings":[],"referenced_globals":["007F57EE DAT_007f57ee = 00h"],"comments":[],"parameters":[{"name":"param_1","type":"void *","length":4,"storage":"Stack[0x4]:4","comment":"","source":"DEFAULT"},{"name":"param_2","type":"int","length":4,"storage":"Stack[0x8]:4","comment":"","source":"DEFAULT"},{"name":"param_3","type":"int","length":4,"storage":"Stack[0xc]:4","comment":"","source":"DEFAULT"}],"locals":[{"name":"local_8","type":"undefined4","length":4,"storage":"Stack[-0x8]:4","comment":"","source":"DEFAULT"},{"name":"local_c","type":"undefined4","length":4,"storage":"Stack[-0xc]:4","comment":"","source":"DEFAULT"}]}
