{"start":"00491E64","end":"00491E77","length":20,"block":".text","classification":"defined_data","base_kind":"defined_data","printable_bytes":7,"non_padding_bytes":15,"executable_pointer_count":5,"valid_relative_call_count":0,"return_opcode_count":0,"import_thunk_entry_count":0,"pointer_targets":["00491E64 -> 00491AD5","00491E68 -> 00491AF2","00491E6C -> 00491B0F","00491E70 -> 00491B2C","00491E74 -> 00491B38"],"raw_inbound_pointer_count":0,"raw_inbound_pointer_sources":[],"raw_pointer_linked_control_flow_entries":0,"raw_pointer_linked_control_flow_sources":[],"inbound_references":["00491ACE -> 00491E64 DATA"]}
