{"id":"00575640","program":"ST.exe","address":"00575640","name":"FUN_00575640","qualified_name":"FUN_00575640","namespace":"Global","source":"DEFAULT","size":714,"signature":"undefined __cdecl FUN_00575640(short * param_1, undefined4 * param_2, short * param_3)","calling_convention":"__cdecl","parameter_count":3,"local_variable_count":7,"stack_frame_size":48,"thunk":false,"thunk_target":"","external":false,"inline":false,"noreturn":false,"varargs":false,"library":false,"body_exported":true,"decompile_status":"ok","tags":[],"callers":[],"callees":["006AAC70 Library::DKW::LIB::FUN_006aac70","006AB060 FreeAndNull","006AB090 FUN_006ab090"],"referenced_strings":[],"referenced_globals":[],"comments":[],"parameters":[{"name":"param_1","type":"short *","length":4,"storage":"Stack[0x4]:4","comment":"","source":"DEFAULT"},{"name":"param_2","type":"undefined4 *","length":4,"storage":"Stack[0x8]:4","comment":"","source":"DEFAULT"},{"name":"param_3","type":"short *","length":4,"storage":"Stack[0xc]:4","comment":"","source":"DEFAULT"}],"locals":[{"name":"local_8","type":"undefined4","length":4,"storage":"Stack[-0x8]:4","comment":"","source":"DEFAULT"},{"name":"local_c","type":"undefined4","length":4,"storage":"Stack[-0xc]:4","comment":"","source":"DEFAULT"},{"name":"local_10","type":"undefined4","length":4,"storage":"Stack[-0x10]:4","comment":"","source":"DEFAULT"},{"name":"local_14","type":"undefined4","length":4,"storage":"Stack[-0x14]:4","comment":"","source":"DEFAULT"},{"name":"local_18","type":"undefined4","length":4,"storage":"Stack[-0x18]:4","comment":"","source":"DEFAULT"},{"name":"local_1c","type":"undefined4","length":4,"storage":"Stack[-0x1c]:4","comment":"","source":"DEFAULT"},{"name":"local_20","type":"undefined4","length":4,"storage":"Stack[-0x20]:4","comment":"","source":"DEFAULT"}]}
