{"id":"005503C0","program":"ST.exe","address":"005503C0","name":"FUN_005503c0","qualified_name":"FUN_005503c0","namespace":"Global","source":"DEFAULT","size":79,"signature":"undefined __thiscall FUN_005503c0(void * this, int param_1)","calling_convention":"__thiscall","parameter_count":2,"local_variable_count":0,"stack_frame_size":8,"thunk":false,"external":false,"inline":false,"noreturn":false,"varargs":false,"decompile_status":"ok","tags":[],"callers":[],"callees":["00404F16 OptPanelTy::Question"],"referenced_strings":[],"referenced_globals":["008016DC DAT_008016dc = 00000000h","00808788 DAT_00808788 = 00000000h"],"comments":[],"parameters":[{"name":"this","type":"void *","length":4,"storage":"ECX:4 (auto)","comment":"","source":"ANALYSIS"},{"name":"param_1","type":"int","length":4,"storage":"Stack[0x4]:4","comment":"","source":"DEFAULT"}],"locals":[]}
