{"start":"00514240","end":"0051426F","length":48,"block":".text","classification":"defined_data","base_kind":"defined_data","printable_bytes":29,"non_padding_bytes":36,"executable_pointer_count":12,"valid_relative_call_count":0,"return_opcode_count":0,"import_thunk_entry_count":0,"pointer_targets":["00514240 -> 0051409A","00514244 -> 00514118","00514248 -> 005140F9","0051424C -> 00514138","00514250 -> 005140D9","00514254 -> 005140BA","00514258 -> 0051407E","0051425C -> 00514197","00514260 -> 005141A2","00514264 -> 00514062","00514268 -> 00514158","0051426C -> 00514178"],"raw_inbound_pointer_count":0,"raw_inbound_pointer_sources":[],"raw_pointer_linked_control_flow_entries":0,"raw_pointer_linked_control_flow_sources":[],"inbound_references":[]}
