{"id":"00734E90","program":"ST.exe","address":"00734E90","name":"FUN_00734e90","qualified_name":"FUN_00734e90","namespace":"Global","source":"DEFAULT","size":388,"signature":"char * __cdecl FUN_00734e90(undefined4 param_1, char * param_2, size_t param_3)","calling_convention":"__cdecl","parameter_count":3,"local_variable_count":4,"stack_frame_size":36,"thunk":false,"external":false,"inline":false,"noreturn":false,"varargs":false,"decompile_status":"ok","tags":[],"callers":["007301E0 FUN_007301e0","00735160 __cftof_g","00735190 __cfltcvt"],"callees":["007351F0 __shift","0073B410 _memset","0073C590 FUN_0073c590","007405A0 FUN_007405a0"],"referenced_strings":[],"referenced_globals":["007F1490 DAT_007f1490 = 2Eh","008571F8 DAT_008571f8 = 00000000h","008571FC DAT_008571fc = 00h","00857200 DAT_00857200 = 00000000h"],"comments":[],"parameters":[{"name":"param_1","type":"undefined4","length":4,"storage":"Stack[0x4]:4","comment":"","source":"DEFAULT"},{"name":"param_2","type":"char *","length":4,"storage":"Stack[0x8]:4","comment":"","source":"DEFAULT"},{"name":"param_3","type":"size_t","length":4,"storage":"Stack[0xc]:4","comment":"","source":"DEFAULT"}],"locals":[{"name":"local_8","type":"undefined4","length":4,"storage":"Stack[-0x8]:4","comment":"","source":"DEFAULT"},{"name":"local_c","type":"undefined4","length":4,"storage":"Stack[-0xc]:4","comment":"","source":"DEFAULT"},{"name":"local_10","type":"undefined4","length":4,"storage":"Stack[-0x10]:4","comment":"","source":"DEFAULT"},{"name":"local_14","type":"undefined4","length":4,"storage":"Stack[-0x14]:4","comment":"","source":"DEFAULT"}]}
