{"id":"0052B760","program":"ST.exe","address":"0052B760","name":"FUN_0052b760","qualified_name":"FUN_0052b760","namespace":"Global","source":"DEFAULT","size":224,"signature":"undefined __thiscall FUN_0052b760(void * this, AnonShape_0052B760_30F4E0D5 * param_1)","calling_convention":"__thiscall","parameter_count":2,"local_variable_count":0,"stack_frame_size":8,"thunk":false,"thunk_target":"","external":false,"inline":false,"noreturn":false,"varargs":false,"library":false,"body_exported":true,"decompile_status":"ok","tags":["RECOVERED_CONTROL_FLOW_LABELS"],"callers":[],"callees":[],"referenced_strings":[],"referenced_globals":["0052B840 switchdataD_0052b840 = 0052b77a","0052B850 switchdataD_0052b850 = 0052b7d2","0080874E DAT_0080874e = 00h","00808A97 DAT_00808a97 = 00000000h"],"comments":[],"parameters":[{"name":"this","type":"void *","length":4,"storage":"ECX:4 (auto)","comment":"","source":"ANALYSIS"},{"name":"param_1","type":"AnonShape_0052B760_30F4E0D5 *","length":4,"storage":"Stack[0x4]:4","comment":"[STPointerShapeApplier] pointer:/SubmarineTitans/Recovered/PointerShapes/AnonShape_0052B760_30F4E0D5; multiple consistent fixed offsets in one persistent target","source":"DEFAULT"}],"locals":[]}
