{"id":"004ED4B0","program":"ST.exe","address":"004ED4B0","name":"FUN_004ed4b0","qualified_name":"FUN_004ed4b0","namespace":"Global","source":"DEFAULT","size":83,"signature":"undefined4 __fastcall FUN_004ed4b0(int param_1)","calling_convention":"__fastcall","parameter_count":1,"local_variable_count":0,"stack_frame_size":4,"thunk":false,"external":false,"inline":false,"noreturn":false,"varargs":false,"library":false,"body_exported":true,"decompile_status":"ok","tags":[],"callers":[],"callees":["006AD4D0 ReportDebugMessage"],"referenced_strings":["007BF5F4 s_Please_Fill_thid_case_!_007bf5f4 = \"Please Fill thid case !\"","007C1670 s_E:\\__titans\\Artem\\TLO_vqb.cpp_007c1670 = \"E:\\\\__titans\\\\Artem\\\\TLO_vqb.cpp\""],"referenced_globals":["004ED508 switchdataD_004ed508 = 004ed4fe","0079AAB8 DAT_0079aab8 = 00000046h","007A4CCC DAT_007a4ccc = 25h %"],"comments":[],"parameters":[{"name":"param_1","type":"int","length":4,"storage":"ECX:4","comment":"","source":"DEFAULT"}],"locals":[]}
