{"start":"006DFF49","end":"006DFFA4","length":92,"block":".text","classification":"seh_funclet_cluster","base_kind":"raw","printable_bytes":23,"non_padding_bytes":74,"executable_pointer_count":0,"valid_relative_call_count":4,"return_opcode_count":2,"import_thunk_entry_count":0,"pointer_targets":[],"raw_inbound_pointer_count":4,"raw_inbound_pointer_sources":["0079E0B4 -> 006DFF49 .rdata","0079E0B8 -> 006DFF4F .rdata","0079E0C0 -> 006DFF77 .rdata","0079E0C4 -> 006DFF7D .rdata"],"raw_pointer_linked_control_flow_entries":0,"raw_pointer_linked_control_flow_sources":[],"inbound_references":[]}
