{"id":"0040495D","program":"ST.exe","address":"0040495D","name":"DeletePlayer","qualified_name":"SettMapMTy::DeletePlayer","namespace":"SettMapMTy","source":"DEFAULT","size":5,"signature":"undefined __thiscall DeletePlayer(SettMapMTy * this, int param_1)","calling_convention":"__thiscall","parameter_count":2,"local_variable_count":0,"stack_frame_size":84,"thunk":true,"thunk_target":"005CFF40 SettMapMTy::DeletePlayer","external":false,"inline":false,"noreturn":false,"varargs":false,"library":false,"body_exported":false,"decompile_status":"skipped_thunk","tags":[],"callers":["005CE0E0 SettMapMTy::NoneSettMap","005D0ED0 SettMapMTy::ChangePlayerList"],"callees":["005CFF40 SettMapMTy::DeletePlayer"],"referenced_strings":[],"referenced_globals":[],"comments":[],"parameters":[{"name":"this","type":"SettMapMTy *","length":4,"storage":"ECX:4 (auto)","comment":"","source":"ANALYSIS"},{"name":"param_1","type":"int","length":4,"storage":"Stack[0x4]:4","comment":"","source":"DEFAULT"}],"locals":[]}
