{"start":"006295EC","end":"00629690","length":165,"block":".text","classification":"defined_data","base_kind":"defined_data","printable_bytes":12,"non_padding_bytes":152,"executable_pointer_count":9,"valid_relative_call_count":0,"return_opcode_count":0,"import_thunk_entry_count":0,"pointer_targets":["006295EC -> 006290A5","006295F0 -> 00629170","006295F4 -> 0062922E","006295F8 -> 00629190","006295FC -> 006291EF","00629600 -> 006291B0","00629604 -> 0062921F","00629608 -> 006291E0","0062960C -> 00629250"],"raw_inbound_pointer_count":0,"raw_inbound_pointer_sources":[],"raw_pointer_linked_control_flow_entries":0,"raw_pointer_linked_control_flow_sources":[],"inbound_references":["00629098 -> 00629610 DATA","0062909E -> 006295EC DATA"]}
