{"id":"0040126C","program":"ST.exe","address":"0040126C","name":"SetCtrl","qualified_name":"MReportTy::SetCtrl","namespace":"MReportTy","source":"DEFAULT","size":5,"signature":"undefined __thiscall SetCtrl(MReportTy * this, int param_1)","calling_convention":"__thiscall","parameter_count":2,"local_variable_count":0,"stack_frame_size":1144,"thunk":true,"external":false,"inline":false,"noreturn":false,"varargs":false,"library":false,"body_exported":true,"decompile_status":"ok","tags":[],"callers":["005BD7A0 MReportTy::InitMReport","005C0E00 MReportTy::SetCtrl"],"callees":[],"referenced_strings":[],"referenced_globals":[],"comments":[],"parameters":[{"name":"this","type":"MReportTy *","length":4,"storage":"ECX:4 (auto)","comment":"","source":"ANALYSIS"},{"name":"param_1","type":"int","length":4,"storage":"Stack[0x4]:4","comment":"","source":"DEFAULT"}],"locals":[]}
