{"id":"004CF640","program":"ST.exe","address":"004CF640","name":"FUN_004cf640","qualified_name":"FUN_004cf640","namespace":"Global","source":"DEFAULT","size":749,"signature":"undefined __thiscall FUN_004cf640(void * this, int * param_1)","calling_convention":"__thiscall","parameter_count":2,"local_variable_count":20,"stack_frame_size":260,"thunk":false,"thunk_target":"","external":false,"inline":false,"noreturn":false,"varargs":false,"library":false,"body_exported":true,"decompile_status":"ok","tags":[],"callers":["00404C96 thunk_FUN_004cf640"],"callees":["00401B59 thunk_FUN_004c9370","00402E32 thunk_FUN_004e6b40","004035DF thunk_FUN_004c7260","0040413D thunk_FUN_004e6a80","004049B7 GetPlayerRaceId","0040571D thunk_FUN_004e6010","006ACC70 DArrayGetElement","006AE1C0 Library::DKW::TBL::FUN_006ae1c0","006AE290 Library::DKW::TBL::DArrayCreate","006B0FD0 FUN_006b0fd0"],"referenced_strings":[],"referenced_globals":["004CF930 switchdataD_004cf930 = 004cf76f","007F4E20 g_playerRuntime = ","007FA174 g_sTAllPlayers_007FA174 = 00000000","007FB240 g_worldGrid = ","00800F10 DAT_00800f10 = 00h","00801330 DAT_00801330 = 00h","008013F0 DAT_008013f0 = 00h","00801450 DAT_00801450 = 00h","00801480 DAT_00801480 = 00h"],"comments":[],"parameters":[{"name":"this","type":"void *","length":4,"storage":"ECX:4 (auto)","comment":"","source":"ANALYSIS"},{"name":"param_1","type":"int *","length":4,"storage":"Stack[0x4]:4","comment":"","source":"DEFAULT"}],"locals":[{"name":"local_8","type":"undefined4","length":4,"storage":"Stack[-0x8]:4","comment":"","source":"DEFAULT"},{"name":"local_c","type":"undefined4","length":4,"storage":"Stack[-0xc]:4","comment":"","source":"DEFAULT"},{"name":"local_10","type":"undefined4","length":4,"storage":"Stack[-0x10]:4","comment":"","source":"DEFAULT"},{"name":"local_14","type":"undefined4","length":4,"storage":"Stack[-0x14]:4","comment":"","source":"DEFAULT"},{"name":"local_18","type":"undefined4","length":4,"storage":"Stack[-0x18]:4","comment":"","source":"DEFAULT"},{"name":"local_1c","type":"undefined4","length":4,"storage":"Stack[-0x1c]:4","comment":"","source":"DEFAULT"},{"name":"local_20","type":"undefined4","length":4,"storage":"Stack[-0x20]:4","comment":"","source":"DEFAULT"},{"name":"local_24","type":"undefined4","length":4,"storage":"Stack[-0x24]:4","comment":"","source":"DEFAULT"},{"name":"local_28","type":"undefined4","length":4,"storage":"Stack[-0x28]:4","comment":"","source":"DEFAULT"},{"name":"local_2c","type":"undefined4","length":4,"storage":"Stack[-0x2c]:4","comment":"","source":"DEFAULT"},{"name":"local_4a","type":"undefined","length":1,"storage":"Stack[-0x4a]:1","comment":"","source":"DEFAULT"},{"name":"local_4c","type":"undefined2","length":2,"storage":"Stack[-0x4c]:2","comment":"","source":"DEFAULT"},{"name":"local_4e","type":"undefined2","length":2,"storage":"Stack[-0x4e]:2","comment":"","source":"DEFAULT"},{"name":"local_50","type":"undefined2","length":2,"storage":"Stack[-0x50]:2","comment":"","source":"DEFAULT"},{"name":"local_52","type":"undefined2","length":2,"storage":"Stack[-0x52]:2","comment":"","source":"DEFAULT"},{"name":"local_53","type":"undefined1","length":1,"storage":"Stack[-0x53]:1","comment":"","source":"DEFAULT"},{"name":"local_54","type":"undefined1","length":1,"storage":"Stack[-0x54]:1","comment":"","source":"DEFAULT"},{"name":"local_58","type":"undefined4","length":4,"storage":"Stack[-0x58]:4","comment":"","source":"DEFAULT"},{"name":"local_5c","type":"undefined4","length":4,"storage":"Stack[-0x5c]:4","comment":"","source":"DEFAULT"},{"name":"local_fc","type":"undefined4","length":4,"storage":"Stack[-0xfc]:4","comment":"","source":"DEFAULT"}]}
