{"id":"006C7610","program":"ST.exe","address":"006C7610","name":"FUN_006c7610","qualified_name":"FUN_006c7610","namespace":"Global","source":"DEFAULT","size":154,"signature":"undefined __stdcall FUN_006c7610(int param_1, int param_2, int param_3, int param_4, uint param_5, uint param_6, int param_7, undefined1 param_8)","calling_convention":"__stdcall","parameter_count":8,"local_variable_count":0,"stack_frame_size":33,"thunk":false,"external":false,"inline":false,"noreturn":false,"varargs":false,"decompile_status":"ok","tags":[],"callers":["005C0B00 FUN_005c0b00","005C8A40 FUN_005c8a40","005E11D0 FUN_005e11d0","005E4300 FUN_005e4300","005E4570 FUN_005e4570"],"callees":["006B4170 FUN_006b4170","006B4FA0 FUN_006b4fa0","006D7A30 FUN_006d7a30"],"referenced_strings":[],"referenced_globals":[],"comments":[],"parameters":[{"name":"param_1","type":"int","length":4,"storage":"Stack[0x4]:4","comment":"","source":"DEFAULT"},{"name":"param_2","type":"int","length":4,"storage":"Stack[0x8]:4","comment":"","source":"DEFAULT"},{"name":"param_3","type":"int","length":4,"storage":"Stack[0xc]:4","comment":"","source":"DEFAULT"},{"name":"param_4","type":"int","length":4,"storage":"Stack[0x10]:4","comment":"","source":"DEFAULT"},{"name":"param_5","type":"uint","length":4,"storage":"Stack[0x14]:4","comment":"","source":"DEFAULT"},{"name":"param_6","type":"uint","length":4,"storage":"Stack[0x18]:4","comment":"","source":"DEFAULT"},{"name":"param_7","type":"int","length":4,"storage":"Stack[0x1c]:4","comment":"","source":"DEFAULT"},{"name":"param_8","type":"undefined1","length":1,"storage":"Stack[0x20]:1","comment":"","source":"DEFAULT"}],"locals":[]}
