{"id":"0074834E","program":"ST.exe","address":"0074834E","name":"FUN_0074834e","qualified_name":"FUN_0074834e","namespace":"Global","source":"DEFAULT","size":46,"signature":"int __thiscall FUN_0074834e(void * this, int * param_1)","calling_convention":"__thiscall","parameter_count":2,"local_variable_count":0,"stack_frame_size":8,"thunk":false,"external":false,"inline":false,"noreturn":false,"varargs":false,"decompile_status":"ok","tags":[],"callers":["0074C77C FUN_0074c77c"],"callees":["00747F68 FUN_00747f68"],"referenced_strings":[],"referenced_globals":["007A1B60 DAT_007a1b60 = 9Dh"],"comments":[],"parameters":[{"name":"this","type":"void *","length":4,"storage":"ECX:4 (auto)","comment":"","source":"ANALYSIS"},{"name":"param_1","type":"int *","length":4,"storage":"Stack[0x4]:4","comment":"","source":"DEFAULT"}],"locals":[]}
