{"id":"004058EE","program":"ST.exe","address":"004058EE","name":"GetMessage","qualified_name":"STAppC::GetMessage","namespace":"STAppC","source":"DEFAULT","size":5,"signature":"undefined4 __thiscall GetMessage(STAppC * this, int param_1)","calling_convention":"__thiscall","parameter_count":2,"local_variable_count":0,"stack_frame_size":2476,"thunk":true,"external":false,"inline":false,"noreturn":false,"varargs":false,"library":false,"body_exported":true,"decompile_status":"ok","tags":[],"callers":["005449B0 CursorClassTy::GetMessage"],"callees":[],"referenced_strings":[],"referenced_globals":[],"comments":[],"parameters":[{"name":"this","type":"STAppC *","length":4,"storage":"ECX:4 (auto)","comment":"","source":"ANALYSIS"},{"name":"param_1","type":"int","length":4,"storage":"Stack[0x4]:4","comment":"","source":"DEFAULT"}],"locals":[]}
