{"id":"0073B0B0","program":"ST.exe","address":"0073B0B0","name":"FUN_0073b0b0","qualified_name":"FUN_0073b0b0","namespace":"Global","source":"DEFAULT","size":135,"signature":"undefined4 __cdecl FUN_0073b0b0(int param_1, int param_2)","calling_convention":"__cdecl","parameter_count":2,"local_variable_count":2,"stack_frame_size":140,"thunk":false,"external":false,"inline":false,"noreturn":false,"varargs":false,"decompile_status":"ok","tags":[],"callers":["0073A9C0 FUN_0073a9c0","0073AD70 FUN_0073ad70"],"callees":["00736C10 _strlen","0073B320 FUN_0073b320","0073B3A0 _GetPrimaryLen"],"referenced_strings":[],"referenced_globals":["00857284 DAT_00857284 = 00000000h","00857294 DAT_00857294 = 00000000h"],"comments":[],"parameters":[{"name":"param_1","type":"int","length":4,"storage":"Stack[0x4]:4","comment":"","source":"DEFAULT"},{"name":"param_2","type":"int","length":4,"storage":"Stack[0x8]:4","comment":"","source":"DEFAULT"}],"locals":[{"name":"local_8","type":"undefined4","length":4,"storage":"Stack[-0x8]:4","comment":"","source":"DEFAULT"},{"name":"local_80","type":"undefined","length":1,"storage":"Stack[-0x80]:1","comment":"","source":"DEFAULT"}]}
