{"start":"0043F074","end":"0043F0A2","length":47,"block":".text","classification":"defined_data","base_kind":"defined_data","printable_bytes":2,"non_padding_bytes":41,"executable_pointer_count":2,"valid_relative_call_count":0,"return_opcode_count":0,"import_thunk_entry_count":0,"pointer_targets":["0043F074 -> 0043EFB8","0043F078 -> 0043EFD6"],"raw_inbound_pointer_count":0,"raw_inbound_pointer_sources":[],"raw_pointer_linked_control_flow_entries":0,"raw_pointer_linked_control_flow_sources":[],"inbound_references":["0043EFAB -> 0043F07C DATA","0043EFB1 -> 0043F074 DATA"]}
