{"id":"005AE050","program":"ST.exe","address":"005AE050","name":"ShowDescription","qualified_name":"ChooseMapTy::ShowDescription","namespace":"ChooseMapTy","source":"USER_DEFINED","size":1613,"signature":"undefined __thiscall ShowDescription(ChooseMapTy * this, uint param_1)","calling_convention":"__thiscall","parameter_count":2,"local_variable_count":13,"stack_frame_size":264,"thunk":false,"thunk_target":"","external":false,"inline":false,"noreturn":false,"varargs":false,"library":false,"body_exported":true,"decompile_status":"ok","tags":["RECOVERED_DEBUG_NAME"],"callers":[],"callees":["00402716 StartSystemTy::LoadMapData","00403229 thunk_FUN_00540760","00404B51 MMsgTy::StatePanel","006A5E40 RaiseInternalException","006AD4D0 ReportDebugMessage","006B35D0 FUN_006b35d0","006B4170 FUN_006b4170","006B54F0 Library::DKW::TBL::FUN_006b54f0","006B5570 FUN_006b5570","006B8280 FUN_006b8280","006E6080 FUN_006e6080","006F0EC0 FUN_006f0ec0","006F1170 cMf32::delete","006F1CE0 cMf32::RecGet","0070A5A0 FUN_0070a5a0","007126E0 ccFntTy::FormIndentSarr","0071AA10 FUN_0071aa10","0072D7F0 Library::MSVCRT::__setjmp3"],"referenced_strings":["007C21D8 s_,.;:!?/\\()[]{}_007c21d8 = \" ,.;:!?/\\\\()[]{}\"","007C9FE4 s_OBJECTIVES_007c9fe4 = \"OBJECTIVES\"","007CC708 s_MISSION_007cc708 = \"MISSION\"","007CC714 s_ADDON_007cc714 = \"ADDON\"","007CC728 s_E:\\__titans\\Start\\load_obj.cpp_007cc728 = \"E:\\\\__titans\\\\Start\\\\load_obj.cpp\"","007CC790 s_MM_MAPB_007cc790 = \"MM_MAPB\"","007CC830 s_ChooseMapTy::ShowDescription_007cc830 = \"ChooseMapTy::ShowDescription\""],"referenced_globals":["0079C060 PTR_s_ADDON_0079c060 = 007cc714","0079C064 PTR_s_MISSION_0079c064 = 007cc708","0079C068 PTR_DAT_0079c068 = 007cc704","0079C06C PTR_DAT_0079c06c = 007c7064","0079C074 PTR_s_OBJECTIVES_0079c074 = 007c9fe4","007A4CCC DAT_007a4ccc = 25h %","007C21EC DAT_007c21ec = 40h @","007C7064 DAT_007c7064 = 53h","007C7065 DAT_007c7065 = 41h","007CC704 DAT_007cc704 = 43h C","007CC854 DAT_007cc854 = 26h","00803400 DAT_00803400 = 00h","00806780 DAT_00806780 = 00000000h","008075A8 DAT_008075a8 = 00000000h","0080874E DAT_0080874e = 00h","008087BE DAT_008087be = 00000000h","0080C4CB DAT_0080c4cb = 00000000h","0080ED16 DAT_0080ed16 = 00h","0080ED1A DAT_0080ed1a = 00h","0081176C DAT_0081176c = 00000000h","00858DF8 g_currentExceptionFrame = 00000000"],"comments":["005AE050 [plate] Recovered from embedded debug metadata: E:\\__titans\\Start\\load_obj.cpp ChooseMapTy::ShowDescription"],"parameters":[{"name":"this","type":"ChooseMapTy *","length":4,"storage":"ECX:4 (auto)","comment":"","source":"ANALYSIS"},{"name":"param_1","type":"uint","length":4,"storage":"Stack[0x4]:4","comment":"","source":"DEFAULT"}],"locals":[{"name":"local_8","type":"undefined4","length":4,"storage":"Stack[-0x8]:4","comment":"","source":"DEFAULT"},{"name":"local_c","type":"undefined4","length":4,"storage":"Stack[-0xc]:4","comment":"","source":"DEFAULT"},{"name":"local_10","type":"undefined4","length":4,"storage":"Stack[-0x10]:4","comment":"","source":"DEFAULT"},{"name":"local_14","type":"undefined4","length":4,"storage":"Stack[-0x14]:4","comment":"","source":"DEFAULT"},{"name":"local_18","type":"undefined4","length":4,"storage":"Stack[-0x18]:4","comment":"","source":"DEFAULT"},{"name":"local_32","type":"undefined2","length":2,"storage":"Stack[-0x32]:2","comment":"","source":"DEFAULT"},{"name":"local_34","type":"undefined2","length":2,"storage":"Stack[-0x34]:2","comment":"","source":"DEFAULT"},{"name":"local_74","type":"undefined","length":1,"storage":"Stack[-0x74]:1","comment":"","source":"DEFAULT"},{"name":"local_78","type":"undefined4","length":4,"storage":"Stack[-0x78]:4","comment":"","source":"DEFAULT"},{"name":"local_b8","type":"undefined","length":1,"storage":"Stack[-0xb8]:1","comment":"","source":"DEFAULT"},{"name":"local_bc","type":"undefined4","length":4,"storage":"Stack[-0xbc]:4","comment":"","source":"DEFAULT"},{"name":"local_fc","type":"undefined","length":1,"storage":"Stack[-0xfc]:1","comment":"","source":"DEFAULT"},{"name":"local_100","type":"undefined4","length":4,"storage":"Stack[-0x100]:4","comment":"","source":"DEFAULT"}]}
