{"id":"006E34C0","program":"ST.exe","address":"006E34C0","name":"FUN_006e34c0","qualified_name":"FUN_006e34c0","namespace":"Global","source":"DEFAULT","size":76,"signature":"undefined __thiscall FUN_006e34c0(void * this, undefined4 param_1, undefined4 param_2)","calling_convention":"__thiscall","parameter_count":3,"local_variable_count":0,"stack_frame_size":12,"thunk":false,"external":false,"inline":false,"noreturn":false,"varargs":false,"decompile_status":"ok","tags":[],"callers":["0056A5F0 FUN_0056a5f0"],"callees":[],"referenced_strings":[],"referenced_globals":["0079E16C PTR_FUN_0079e16c = 006e3510","00856D6C DAT_00856d6c = 00000000h"],"comments":[],"parameters":[{"name":"this","type":"void *","length":4,"storage":"ECX:4 (auto)","comment":"","source":"ANALYSIS"},{"name":"param_1","type":"undefined4","length":4,"storage":"Stack[0x4]:4","comment":"","source":"DEFAULT"},{"name":"param_2","type":"undefined4","length":4,"storage":"Stack[0x8]:4","comment":"","source":"DEFAULT"}],"locals":[]}
