{"id":"00405E2F","program":"ST.exe","address":"00405E2F","name":"thunk_FUN_005252c0","qualified_name":"thunk_FUN_005252c0","namespace":"Global","source":"DEFAULT","size":5,"signature":"undefined __cdecl thunk_FUN_005252c0(int param_1)","calling_convention":"__cdecl","parameter_count":1,"local_variable_count":0,"stack_frame_size":84,"thunk":true,"external":false,"inline":false,"noreturn":false,"varargs":false,"decompile_status":"ok","tags":[],"callers":["004EE4D0 BehPanelTy::GetMessage","004EF6D0 BldBoatPanelTy::GetMessage","004F0210 BldLabPanelTy::GetMessage","004F1080 BldObjPanelTy::GetMessage","004F80A0 CPanelTy::PaintTV","004F96A0 CPanelTy::PlayBrief","004F9ED0 CPanelTy::SwitchCPanel","004FB060 CPanelTy::GetMessage","004FF110 CPanelTy::SwitchTV","005007A0 CPanelTy::SetNewDeep","00503BB0 CPanelTy::SetCmdBoat","0050F430 CPanelTy::SetCmdObj","005107C0 FrmPanelTy::GetMessage","00511DF0 HelpPanelTy::SwitchOptPanel","0051DDD0 HelpPanelTy::GetMessage","00522D40 IntercomPanelTy::SwitchIntercomPanel","0052AFE0 FUN_0052afe0","0052B330 FUN_0052b330","0052F2B0 OptPanelTy::SwitchOptPanel","0052F7E0 OptPanelTy::SwitchOptPanelOff","00533D10 OptPanelTy::GetMessage","005395B0 PausePanelTy::SwitchPausePanel","0053A6B0 PlayPanelTy::SwitchOptPanel","0053AFB0 PlayPanelTy::GetMessage","0053CA80 ResearchPanelTy::GetMessage","0053E760 SpecPanelTy::SwitchPanel","0053EB70 SpecPanelTy::GetMessage","0053F3A0 ProdPanelTy::SwitchPanel","005400F0 ProdPanelTy::GetMessage","00542F40 InterSystemC::GetMessage"],"callees":[],"referenced_strings":[],"referenced_globals":[],"comments":[],"parameters":[{"name":"param_1","type":"int","length":4,"storage":"Stack[0x4]:4","comment":"","source":"DEFAULT"}],"locals":[]}
