{"id":"0041AEE0","program":"ST.exe","address":"0041AEE0","name":"FUN_0041aee0","qualified_name":"FUN_0041aee0","namespace":"Global","source":"DEFAULT","size":31,"signature":"undefined __stdcall FUN_0041aee0(void)","calling_convention":"__stdcall","parameter_count":0,"local_variable_count":0,"stack_frame_size":4,"thunk":false,"external":false,"inline":false,"noreturn":false,"varargs":false,"decompile_status":"ok","tags":[],"callers":[],"callees":["00404C55 thunk_FUN_0043fc50"],"referenced_strings":[],"referenced_globals":["007FA174 DAT_007fa174 = 00000000h"],"comments":[],"parameters":[],"locals":[]}
