{"start":"004F1BC0","end":"004F1BE7","length":40,"block":".text","classification":"defined_data","base_kind":"defined_data","printable_bytes":15,"non_padding_bytes":30,"executable_pointer_count":10,"valid_relative_call_count":0,"return_opcode_count":0,"import_thunk_entry_count":0,"pointer_targets":["004F1BC0 -> 004F1A14","004F1BC4 -> 004F1A2F","004F1BC8 -> 004F1A4A","004F1BCC -> 004F1A65","004F1BD0 -> 004F1A80","004F1BD4 -> 004F1AD2","004F1BD8 -> 004F1AED","004F1BDC -> 004F1B08","004F1BE0 -> 004F1B23","004F1BE4 -> 004F1B3E"],"raw_inbound_pointer_count":0,"raw_inbound_pointer_sources":[],"raw_pointer_linked_control_flow_entries":0,"raw_pointer_linked_control_flow_sources":[],"inbound_references":["004F1A0D -> 004F1BC0 DATA","004F1ACB -> 004F1BD4 DATA"]}
