{"start":"005051B0","end":"005051DB","length":44,"block":".text","classification":"defined_data","base_kind":"defined_data","printable_bytes":30,"non_padding_bytes":33,"executable_pointer_count":11,"valid_relative_call_count":0,"return_opcode_count":0,"import_thunk_entry_count":0,"pointer_targets":["005051B0 -> 00505143","005051B4 -> 00505102","005051B8 -> 0050510E","005051BC -> 0050511A","005051C0 -> 00505126","005051C4 -> 00505143","005051C8 -> 0050514C","005051CC -> 00505158","005051D0 -> 00505164","005051D4 -> 00505170","005051D8 -> 0050517C"],"raw_inbound_pointer_count":0,"raw_inbound_pointer_sources":[],"raw_pointer_linked_control_flow_entries":0,"raw_pointer_linked_control_flow_sources":[],"inbound_references":["005050FB -> 005051B0 DATA","0050513C -> 005051C4 DATA"]}
