{"id":"0055B9F0","program":"ST.exe","address":"0055B9F0","name":"FUN_0055b9f0","qualified_name":"FUN_0055b9f0","namespace":"Global","source":"DEFAULT","size":127,"signature":"uint __thiscall FUN_0055b9f0(void * this, char * param_1)","calling_convention":"__thiscall","parameter_count":2,"local_variable_count":0,"stack_frame_size":8,"thunk":false,"external":false,"inline":false,"noreturn":false,"varargs":false,"library":false,"body_exported":true,"decompile_status":"ok","tags":[],"callers":[],"callees":[],"referenced_strings":[],"referenced_globals":[],"comments":[],"parameters":[{"name":"this","type":"void *","length":4,"storage":"ECX:4 (auto)","comment":"","source":"ANALYSIS"},{"name":"param_1","type":"char *","length":4,"storage":"Stack[0x4]:4","comment":"","source":"DEFAULT"}],"locals":[]}
