{"id":"00401C0D","program":"ST.exe","address":"00401C0D","name":"thunk_FUN_005cbbe0","qualified_name":"thunk_FUN_005cbbe0","namespace":"Global","source":"DEFAULT","size":5,"signature":"int __thiscall thunk_FUN_005cbbe0(void * this, AnonShape_005CBBE0_2D1CAA09 * param_1)","calling_convention":"__thiscall","parameter_count":2,"local_variable_count":0,"stack_frame_size":8,"thunk":true,"thunk_target":"005CBBE0 FUN_005cbbe0","external":false,"inline":false,"noreturn":false,"varargs":false,"library":false,"body_exported":false,"decompile_status":"skipped_thunk","tags":[],"callers":["005D1400 SettMapMTy::GetMessage","005D5560 SettMapSTy::GetMessage"],"callees":["005CBBE0 FUN_005cbbe0"],"referenced_strings":[],"referenced_globals":[],"comments":[],"parameters":[{"name":"this","type":"void *","length":4,"storage":"ECX:4 (auto)","comment":"","source":"ANALYSIS"},{"name":"param_1","type":"AnonShape_005CBBE0_2D1CAA09 *","length":4,"storage":"Stack[0x4]:4","comment":"[STPointerShapeApplier] pointer:/SubmarineTitans/Recovered/PointerShapes/AnonShape_005CBBE0_2D1CAA09; consistent nested offsets through a pointer field in one persistent target","source":"DEFAULT"}],"locals":[]}
