{"id":"0042A290","program":"ST.exe","address":"0042A290","name":"LoadLand","qualified_name":"LoadLand","namespace":"Global","source":"USER_DEFINED","size":1003,"signature":"short * __cdecl LoadLand(cMf32 * param_1, char * text)","calling_convention":"__cdecl","parameter_count":2,"local_variable_count":14,"stack_frame_size":256,"thunk":false,"thunk_target":"","external":false,"inline":false,"noreturn":false,"varargs":false,"library":false,"body_exported":true,"decompile_status":"ok","tags":["RECOVERED_PROTOTYPE","RECOVERED_SOURCE_FILE","RECOVERED_SOURCE_NAME"],"callers":[],"callees":["004010D7 LandInit","00403472 cLoadingTy::SetState","004045ED thunk_FUN_00428e50","00404D8B cLoadingTy::SetProcess","006A5E40 RaiseInternalException","006AAC70 Library::DKW::LIB::FUN_006aac70","006AD4D0 ReportDebugMessage","006AE110 FUN_006ae110","006AE1C0 Library::DKW::TBL::FUN_006ae1c0","006AE290 Library::DKW::TBL::FUN_006ae290","006B0140 FUN_006b0140","006B04D0 FUN_006b04d0","006DBCA0 FUN_006dbca0","006DBCF0 FUN_006dbcf0","006DC050 FUN_006dc050","006DD610 FUN_006dd610","006DD790 FUN_006dd790","006DD800 FUN_006dd800","006DDBE0 FUN_006ddbe0","006DDD50 FUN_006ddd50","006EF640 Library::Ourlib::MFSTMAP::mfTMapLoad","0072D7F0 Library::MSVCRT::__setjmp3","0072E150 Library::MSVCRT::FUN_0072e150","0072E288 Library::MSVCRT::__ftol","0072E2B0 Library::MSVCRT::FUN_0072e2b0","EXTERNAL:00000080 USER32.DLL::wsprintfA"],"referenced_strings":["007A5FDC s_E:\\__titans\\tload.cpp_007a5fdc = \"E:\\\\__titans\\\\tload.cpp\"","007A5FF8 s_LoadLand_007a5ff8 = \"LoadLand\""],"referenced_globals":["007A4CCC DAT_007a4ccc = 25h %","007ED77C g_overwriteContext_007ED77C = 1h","007F4E00 DAT_007f4e00 = 00000000h","00802A58 DAT_00802a58 = 00000000h","00806760 g_cMf32_00806760 = 00000000","0080679C DAT_0080679c = 00000000h","00807618 HINSTANCE_00807618 = 00000000","00858DF8 g_currentExceptionFrame = 00000000","0085BDE8 PTR_wsprintfA_0085bde8 = 0045c5a0"],"comments":["0042A290 [plate] [STSourceProvenanceApplier begin] Recovered source file: E:\\__titans\\tload.cpp Diagnostic line evidence: 1166 | 1282 | 1283 (metadata/report site, not the function definition) [STSourceProvenanceApplier end] [STPrototypeApplier] Propagated parameter 1. Evidence: 00576EF0 -> 0042A290 @ 00576F31 [STPrototypeApplier] Propagated parameter 0. Evidence: 00576EF0 -> 0042A290 @ 00576F31"],"parameters":[{"name":"param_1","type":"cMf32 *","length":4,"storage":"Stack[0x4]:4","comment":"","source":"DEFAULT"},{"name":"text","type":"char *","length":4,"storage":"Stack[0x8]:4","comment":"","source":"ANALYSIS"}],"locals":[{"name":"local_8","type":"undefined4","length":4,"storage":"Stack[-0x8]:4","comment":"","source":"DEFAULT"},{"name":"local_c","type":"undefined4","length":4,"storage":"Stack[-0xc]:4","comment":"","source":"DEFAULT"},{"name":"local_10","type":"undefined4","length":4,"storage":"Stack[-0x10]:4","comment":"","source":"DEFAULT"},{"name":"local_14","type":"undefined4","length":4,"storage":"Stack[-0x14]:4","comment":"","source":"DEFAULT"},{"name":"local_18","type":"undefined4","length":4,"storage":"Stack[-0x18]:4","comment":"","source":"DEFAULT"},{"name":"local_1c","type":"undefined4","length":4,"storage":"Stack[-0x1c]:4","comment":"","source":"DEFAULT"},{"name":"local_20","type":"undefined4","length":4,"storage":"Stack[-0x20]:4","comment":"","source":"DEFAULT"},{"name":"local_24","type":"undefined4","length":4,"storage":"Stack[-0x24]:4","comment":"","source":"DEFAULT"},{"name":"local_28","type":"undefined4","length":4,"storage":"Stack[-0x28]:4","comment":"","source":"DEFAULT"},{"name":"local_2c","type":"undefined4","length":4,"storage":"Stack[-0x2c]:4","comment":"","source":"DEFAULT"},{"name":"local_30","type":"undefined4","length":4,"storage":"Stack[-0x30]:4","comment":"","source":"DEFAULT"},{"name":"local_70","type":"undefined","length":1,"storage":"Stack[-0x70]:1","comment":"","source":"DEFAULT"},{"name":"local_74","type":"undefined4","length":4,"storage":"Stack[-0x74]:4","comment":"","source":"DEFAULT"},{"name":"local_f4","type":"undefined","length":1,"storage":"Stack[-0xf4]:1","comment":"","source":"DEFAULT"}]}
