{"id":"0058D750","program":"ST.exe","address":"0058D750","name":"STSharkC","qualified_name":"STSharkC::STSharkC","namespace":"STSharkC","source":"ANALYSIS","size":78,"signature":"STSharkC * __thiscall STSharkC(STSharkC * this)","calling_convention":"__thiscall","parameter_count":1,"local_variable_count":0,"stack_frame_size":4,"thunk":false,"thunk_target":"","external":false,"inline":false,"noreturn":false,"varargs":false,"library":false,"body_exported":true,"decompile_status":"ok","tags":["RECOVERED_CONSTRUCTOR","RECOVERED_PROTOTYPE"],"callers":[],"callees":["00401316 thunk_FUN_004ab810","00401933 STGameObjC::STGameObjC"],"referenced_strings":[],"referenced_globals":["0079BE80 STSharkCVTable = ","0079BFE0 VTable_0079BFE0 = "],"comments":["0058D750 [plate] [STConstructorApplier] Recovered constructor candidate. VTable: 0079BE80 (store 0058D77B) Evidence: final_vptr=0079BE80; returns_this=true; calls_before=2; field_writes_after=3; table_confidence=high [STPrototypeApplier] Propagated return. Evidence: 0058D750 returns STSharkC::STSharkC this @ 0058D79D"],"parameters":[{"name":"this","type":"STSharkC *","length":4,"storage":"ECX:4 (auto)","comment":"","source":"ANALYSIS"}],"locals":[]}
