{"id":"00401E65","program":"ST.exe","address":"00401E65","name":"thunk_FUN_00635f50","qualified_name":"thunk_FUN_00635f50","namespace":"Global","source":"DEFAULT","size":5,"signature":"undefined __fastcall thunk_FUN_00635f50(int * param_1)","calling_convention":"__fastcall","parameter_count":1,"local_variable_count":0,"stack_frame_size":12,"thunk":true,"external":false,"inline":false,"noreturn":false,"varargs":false,"decompile_status":"ok","tags":[],"callers":["00636060 FUN_00636060"],"callees":[],"referenced_strings":[],"referenced_globals":[],"comments":[],"parameters":[{"name":"param_1","type":"int *","length":4,"storage":"ECX:4","comment":"","source":"DEFAULT"}],"locals":[]}
